[
	{
		"name": "Fish",
		"icon": "fish.png",
		"types": ["Unmarked", "Fish"],
		"left": 90.0,
		"bottom": 552.2,
		"auto_adjust": true
	}, {
		"name": "Fish",
		"icon": "fish.png",
		"types": ["Unmarked", "Fish"],
		"left": 98.4,
		"bottom": 441.3,
		"auto_adjust": true
	}, {
		"name": "Fish",
		"icon": "fish.png",
		"types": ["Unmarked", "Fish"],
		"left": 139.9,
		"bottom": 321.4,
		"auto_adjust": true
	}, {
		"name": "Fish",
		"icon": "fish.png",
		"types": ["Unmarked", "Fish"],
		"left": 745.7,
		"bottom": 156.7,
		"auto_adjust": true
	}, {
		"name": "Fish",
		"icon": "fish.png",
		"types": ["Unmarked", "Fish"],
		"left": 776.3,
		"bottom": 131.1,
		"auto_adjust": true
	}, {
		"name": "Fish",
		"icon": "fish.png",
		"types": ["Unmarked", "Fish"],
		"left": 809.2,
		"bottom": 75.1,
		"auto_adjust": true
	}, {
		"name": "Fish",
		"icon": "fish.png",
		"types": ["Unmarked", "Fish"],
		"left": 910.1,
		"bottom": 74.0,
		"auto_adjust": true
	}, {
		"name": "Fish",
		"icon": "fish.png",
		"types": ["Unmarked", "Fish"],
		"left": 1296.4,
		"bottom": 1087.7,
		"auto_adjust": true
	}, {
		"name": "Fish",
		"icon": "fish.png",
		"types": ["Unmarked", "Fish"],
		"left": 1329.7,
		"bottom": 1110.8,
		"auto_adjust": true
	}, {
		"name": "Fish",
		"icon": "fish.png",
		"types": ["Unmarked", "Fish"],
		"left": 1362.2,
		"bottom": 1566.5,
		"auto_adjust": true
	}, {
		"name": "Fish",
		"icon": "fish.png",
		"types": ["Unmarked", "Fish"],
		"left": 1392.2,
		"bottom": 1582.1,
		"auto_adjust": true
	}, {
		"name": "Fish",
		"icon": "fish.png",
		"types": ["Unmarked", "Fish"],
		"left": 1329.8,
		"bottom": 1680.2,
		"auto_adjust": true
	}, {
		"name": "Fish",
		"icon": "fish.png",
		"types": ["Unmarked", "Fish"],
		"left": 1309.4,
		"bottom": 1687.9,
		"auto_adjust": true
	}, {
		"name": "Fish",
		"icon": "fish.png",
		"types": ["Unmarked", "Fish"],
		"left": 1701.3,
		"bottom": 1789.0,
		"auto_adjust": true
	}, {
		"name": "Fish",
		"icon": "fish.png",
		"types": ["Unmarked", "Fish"],
		"left": 1733.6,
		"bottom": 1773.3,
		"auto_adjust": true
	}, {
		"name": "Fish",
		"icon": "fish.png",
		"types": ["Unmarked", "Fish"],
		"left": 1755.6,
		"bottom": 1746.2,
		"auto_adjust": true
	}, {
		"name": "Fish",
		"icon": "fish.png",
		"types": ["Unmarked", "Fish"],
		"left": 1598.2,
		"bottom": 1559.9,
		"auto_adjust": true
	}, {
		"name": "Fish",
		"icon": "fish.png",
		"types": ["Unmarked", "Fish"],
		"left": 929.1,
		"bottom": 1627.4,
		"auto_adjust": true
	}, {
		"name": "Fish",
		"icon": "fish.png",
		"types": ["Unmarked", "Fish"],
		"left": 1013.5,
		"bottom": 1681.4,
		"auto_adjust": true
	}, {
		"name": "Fish",
		"icon": "fish.png",
		"types": ["Unmarked", "Fish"],
		"left": 1061.0,
		"bottom": 1662.2,
		"auto_adjust": true
	}, {
		"name": "Fish",
		"icon": "fish.png",
		"types": ["Unmarked", "Fish"],
		"left": 1053.8,
		"bottom": 1755.6,
		"auto_adjust": true
	}, {
		"name": "Fish",
		"icon": "fish.png",
		"types": ["Unmarked", "Fish"],
		"left": 1098.4,
		"bottom": 1768.6,
		"auto_adjust": true
	}, {
		"name": "Fish",
		"icon": "fish.png",
		"types": ["Unmarked", "Fish"],
		"left": 873.3,
		"bottom": 1688.2,
		"auto_adjust": true
	}, {
		"name": "Fish",
		"icon": "fish.png",
		"types": ["Unmarked", "Fish"],
		"left": 756.6,
		"bottom": 1655.6,
		"auto_adjust": true
	}, {
		"name": "Fish",
		"icon": "fish.png",
		"types": ["Unmarked", "Fish"],
		"left": 727.4,
		"bottom": 1653.3,
		"auto_adjust": true
	}
]